docta/__init__.py
docta/version.py
docta/apis/__init__.py
docta/apis/detect.py
docta/apis/diagnose.py
docta/apis/train.py
docta/core/__init__.py
docta/core/core_utils.py
docta/core/get_lr_score.py
docta/core/hoc.py
docta/core/knn.py
docta/core/preprocess.py
docta/core/report.py
docta/datasets/__init__.py
docta/datasets/cifar.py
docta/datasets/clothing1m.py
docta/datasets/csv_loder.py
docta/datasets/customize.py
docta/datasets/customize_img_folder.py
docta/datasets/data_utils.py
docta/datasets/hh_rlhf.py
docta/models/__init__.py
docta/models/backbones/__init__.py
docta/models/backbones/mlp.py
docta/models/backbones/resnet.py
docta/models/backbones/resnet_lowres.py
docta/models/loss_funcs/__init__.py
docta/models/loss_funcs/accuracy.py
docta/models/loss_funcs/cross_entropy_loss.py
docta/models/loss_funcs/loss_correction.py
docta/models/loss_funcs/loss_utils.py
docta/models/loss_funcs/peer_loss.py
docta/utils/LexRank.py
docta/utils/__init__.py
docta/utils/config.py
docta/utils/utils.py
docta.ai-0.3.dist-info/LICENSE.md
docta.ai-0.3.dist-info/METADATA
docta.ai-0.3.dist-info/WHEEL
docta.ai-0.3.dist-info/top_level.txt
docta.ai-0.3.dist-info/RECORD
